README.rst
setup.py
wsl/__init__.py
wsl/database.py
wsl/domain.py
wsl/exceptions.py
wsl/format.py
wsl/parse.py
wsl/schema.py
wsl.egg-info/PKG-INFO
wsl.egg-info/SOURCES.txt
wsl.egg-info/dependency_links.txt
wsl.egg-info/top_level.txt