Metadata-Version: 1.1
Name: wsl
Version: 0.8
Summary: Library for reading and writing WSL databases
Home-page: http://jstimpfle.de/projects/wsl/main.html
Author: Jens Stimpfle
Author-email: jfs@jstimpfle.de
License: MIT
Keywords: database development administration plain-text
Platform: UNKNOWN
Classifier: Development Status :: 3 - Alpha
Classifier: Intended Audience :: Developers
Classifier: Intended Audience :: System Administrators
Classifier: Intended Audience :: Other Audience
Classifier: Topic :: Software Development :: Build Tools
Classifier: Topic :: Database
Classifier: License :: OSI Approved :: MIT License
Classifier: Programming Language :: Python :: 3
Classifier: Programming Language :: Python :: 3.3
Classifier: Programming Language :: Python :: 3.4
Classifier: Programming Language :: Python :: 3.5
